validate_pip_version/__init__.py
validate_pip_version/__main__.py
validate_pip_version-1.0.5.dist-info/LICENSE
validate_pip_version-1.0.5.dist-info/METADATA
validate_pip_version-1.0.5.dist-info/WHEEL
validate_pip_version-1.0.5.dist-info/entry_points.txt
validate_pip_version-1.0.5.dist-info/top_level.txt
validate_pip_version-1.0.5.dist-info/RECORD
