Metadata-Version: 2.1
Name: validate-pip-version
Version: 1.0.5
Summary: CLI tool to validate the version of a local PIP package against its currently published version. Intended to be used as part of a CI build.
Home-page: https://github.com/werzl/validate-pip-version
Author: werzl
Author-email: werzl.mail@gmail.com
License: UNKNOWN
Platform: UNKNOWN
Classifier: Programming Language :: Python :: 3.8
Requires-Python: >=3.6
Requires-Dist: Click (>=7.0)
